{
  "minecraft:recipes/redstone/lever": {
    "criteria": {
      "has_cobblestone": "2023-06-08 23:12:03 +0200"
    },
    "done": true
  },
  "minecraft:recipes/decorations/ladder": {
    "criteria": {
      "has_stick": "2023-06-08 23:08:37 +0200"
    },
    "done": true
  },
  "minecraft:recipes/transportation/mangrove_boat": {
    "criteria": {
      "in_water": "2023-06-08 23:09:28 +0200"
    },
    "done": true
  },
  "minecraft:recipes/decorations/torch": {
    "criteria": {
      "has_stone_pickaxe": "2023-06-08 23:13:25 +0200"
    },
    "done": true
  },
  "minecraft:recipes/food/cooked_salmon_from_smoking": {
    "criteria": {
      "has_salmon": "2023-06-08 23:14:10 +0200"
    },
    "done": true
  },
  "minecraft:recipes/building_blocks/jungle_wood": {
    "criteria": {
      "has_log": "2023-06-08 23:09:39 +0200"
    },
    "done": true
  },
  "minecraft:recipes/building_blocks/jungle_planks": {
    "criteria": {
      "has_logs": "2023-06-08 23:09:39 +0200"
    },
    "done": true
  },
  "minecraft:recipes/combat/stone_sword": {
    "criteria": {
      "has_cobblestone": "2023-06-08 23:12:03 +0200"
    },
    "done": true
  },
  "minecraft:recipes/decorations/cobblestone_wall": {
    "criteria": {
      "has_cobblestone": "2023-06-08 23:12:03 +0200"
    },
    "done": true
  },
  "minecraft:recipes/tools/stone_pickaxe": {
    "criteria": {
      "has_cobblestone": "2023-06-08 23:12:03 +0200"
    },
    "done": true
  },
  "minecraft:recipes/tools/stone_axe": {
    "criteria": {
      "has_cobblestone": "2023-06-08 23:12:03 +0200"
    },
    "done": true
  },
  "minecraft:recipes/decorations/campfire": {
    "criteria": {
      "has_stick": "2023-06-08 23:08:37 +0200"
    },
    "done": true
  },
  "minecraft:recipes/redstone/jungle_trapdoor": {
    "criteria": {
      "has_planks": "2023-06-08 23:10:05 +0200"
    },
    "done": true
  },
  "minecraft:recipes/tools/wooden_hoe": {
    "criteria": {
      "has_stick": "2023-06-08 23:08:37 +0200"
    },
    "done": true
  },
  "minecraft:story/mine_stone": {
    "criteria": {
      "get_stone": "2023-06-08 23:12:03 +0200"
    },
    "done": true
  },
  "minecraft:recipes/decorations/furnace": {
    "criteria": {
      "has_cobblestone": "2023-06-08 23:12:03 +0200"
    },
    "done": true
  },
  "minecraft:recipes/misc/charcoal": {
    "criteria": {
      "has_log": "2023-06-08 23:09:39 +0200"
    },
    "done": true
  },
  "minecraft:recipes/tools/wooden_pickaxe": {
    "criteria": {
      "has_stick": "2023-06-08 23:08:37 +0200"
    },
    "done": true
  },
  "minecraft:recipes/food/cooked_salmon_from_campfire_cooking": {
    "criteria": {
      "has_salmon": "2023-06-08 23:14:10 +0200"
    },
    "done": true
  },
  "minecraft:story/upgrade_tools": {
    "criteria": {
      "stone_pickaxe": "2023-06-08 23:13:25 +0200"
    },
    "done": true
  },
  "minecraft:recipes/tools/wooden_axe": {
    "criteria": {
      "has_stick": "2023-06-08 23:08:37 +0200"
    },
    "done": true
  },
  "minecraft:recipes/decorations/jungle_sign": {
    "criteria": {
      "has_planks": "2023-06-08 23:10:05 +0200"
    },
    "done": true
  },
  "minecraft:recipes/food/cooked_salmon": {
    "criteria": {
      "has_salmon": "2023-06-08 23:14:10 +0200"
    },
    "done": true
  },
  "minecraft:recipes/redstone/jungle_door": {
    "criteria": {
      "has_planks": "2023-06-08 23:10:05 +0200"
    },
    "done": true
  },
  "minecraft:recipes/decorations/crafting_table": {
    "criteria": {
      "unlock_right_away": "2023-06-08 23:06:48 +0200"
    },
    "done": true
  },
  "minecraft:recipes/tools/wooden_shovel": {
    "criteria": {
      "has_stick": "2023-06-08 23:08:37 +0200"
    },
    "done": true
  },
  "minecraft:recipes/misc/stick": {
    "criteria": {
      "has_planks": "2023-06-08 23:10:05 +0200"
    },
    "done": true
  },
  "minecraft:recipes/building_blocks/cobblestone_slab": {
    "criteria": {
      "has_cobblestone": "2023-06-08 23:12:03 +0200"
    },
    "done": true
  },
  "minecraft:recipes/building_blocks/cobblestone_slab_from_cobblestone_stonecutting": {
    "criteria": {
      "has_cobblestone": "2023-06-08 23:12:03 +0200"
    },
    "done": true
  },
  "minecraft:recipes/transportation/acacia_boat": {
    "criteria": {
      "in_water": "2023-06-08 23:09:28 +0200"
    },
    "done": true
  },
  "minecraft:recipes/transportation/cherry_boat": {
    "criteria": {
      "in_water": "2023-06-08 23:09:28 +0200"
    },
    "done": true
  },
  "minecraft:adventure/root": {
    "criteria": {
      "killed_something": "2023-06-08 23:14:09 +0200"
    },
    "done": true
  },
  "minecraft:recipes/decorations/jungle_fence": {
    "criteria": {
      "has_planks": "2023-06-08 23:10:05 +0200"
    },
    "done": true
  },
  "minecraft:recipes/redstone/jungle_pressure_plate": {
    "criteria": {
      "has_planks": "2023-06-08 23:10:05 +0200"
    },
    "done": true
  },
  "minecraft:recipes/combat/wooden_sword": {
    "criteria": {
      "has_stick": "2023-06-08 23:08:37 +0200"
    },
    "done": true
  },
  "minecraft:recipes/building_blocks/stone": {
    "criteria": {
      "has_cobblestone": "2023-06-08 23:12:03 +0200"
    },
    "done": true
  },
  "minecraft:adventure/adventuring_time": {
    "criteria": {
      "minecraft:wooded_badlands": "2023-06-08 23:08:38 +0200",
      "minecraft:badlands": "2023-06-08 23:06:49 +0200",
      "minecraft:sparse_jungle": "2023-06-08 23:11:40 +0200",
      "minecraft:river": "2023-06-08 23:09:29 +0200",
      "minecraft:jungle": "2023-06-08 23:09:34 +0200"
    },
    "done": false
  },
  "minecraft:recipes/transportation/bamboo_raft": {
    "criteria": {
      "in_water": "2023-06-08 23:09:28 +0200"
    },
    "done": true
  },
  "minecraft:recipes/decorations/barrel": {
    "criteria": {
      "has_planks": "2023-06-08 23:10:05 +0200"
    },
    "done": true
  },
  "minecraft:recipes/decorations/cobblestone_wall_from_cobblestone_stonecutting": {
    "criteria": {
      "has_cobblestone": "2023-06-08 23:12:03 +0200"
    },
    "done": true
  },
  "minecraft:recipes/misc/stick_from_bamboo_item": {
    "criteria": {
      "has_bamboo": "2023-06-08 23:15:08 +0200"
    },
    "done": true
  },
  "minecraft:recipes/building_blocks/cobblestone_stairs_from_cobblestone_stonecutting": {
    "criteria": {
      "has_cobblestone": "2023-06-08 23:12:03 +0200"
    },
    "done": true
  },
  "minecraft:recipes/transportation/spruce_boat": {
    "criteria": {
      "in_water": "2023-06-08 23:09:28 +0200"
    },
    "done": true
  },
  "minecraft:recipes/redstone/jungle_button": {
    "criteria": {
      "has_planks": "2023-06-08 23:10:05 +0200"
    },
    "done": true
  },
  "minecraft:recipes/building_blocks/cobblestone_stairs": {
    "criteria": {
      "has_cobblestone": "2023-06-08 23:12:03 +0200"
    },
    "done": true
  },
  "minecraft:recipes/building_blocks/bamboo_block": {
    "criteria": {
      "has_bamboo": "2023-06-08 23:15:08 +0200"
    },
    "done": true
  },
  "minecraft:recipes/transportation/birch_boat": {
    "criteria": {
      "in_water": "2023-06-08 23:09:28 +0200"
    },
    "done": true
  },
  "minecraft:recipes/tools/stone_hoe": {
    "criteria": {
      "has_cobblestone": "2023-06-08 23:12:03 +0200"
    },
    "done": true
  },
  "minecraft:recipes/transportation/oak_boat": {
    "criteria": {
      "in_water": "2023-06-08 23:09:28 +0200"
    },
    "done": true
  },
  "minecraft:recipes/decorations/scaffolding": {
    "criteria": {
      "has_bamboo": "2023-06-08 23:15:08 +0200"
    },
    "done": true
  },
  "minecraft:recipes/tools/stone_shovel": {
    "criteria": {
      "has_cobblestone": "2023-06-08 23:12:03 +0200"
    },
    "done": true
  },
  "minecraft:story/root": {
    "criteria": {
      "crafting_table": "2023-06-08 23:11:25 +0200"
    },
    "done": true
  },
  "minecraft:recipes/building_blocks/jungle_slab": {
    "criteria": {
      "has_planks": "2023-06-08 23:10:05 +0200"
    },
    "done": true
  },
  "minecraft:recipes/transportation/jungle_boat": {
    "criteria": {
      "in_water": "2023-06-08 23:09:28 +0200"
    },
    "done": true
  },
  "minecraft:recipes/building_blocks/jungle_stairs": {
    "criteria": {
      "has_planks": "2023-06-08 23:10:05 +0200"
    },
    "done": true
  },
  "minecraft:recipes/transportation/dark_oak_boat": {
    "criteria": {
      "in_water": "2023-06-08 23:09:28 +0200"
    },
    "done": true
  },
  "minecraft:recipes/redstone/jungle_fence_gate": {
    "criteria": {
      "has_planks": "2023-06-08 23:10:05 +0200"
    },
    "done": true
  },
  "DataVersion": 3463
}